LICENSE
MANIFEST.in
README.md
setup.py
tapioca_disqus/__init__.py
tapioca_disqus/tapioca_disqus.py
tapioca_disqus.egg-info/PKG-INFO
tapioca_disqus.egg-info/SOURCES.txt
tapioca_disqus.egg-info/dependency_links.txt
tapioca_disqus.egg-info/not-zip-safe
tapioca_disqus.egg-info/requires.txt
tapioca_disqus.egg-info/top_level.txt
tapioca_disqus/__pycache__/__init__.cpython-34.pyc
tapioca_disqus/__pycache__/tapioca_disqus.cpython-34.pyc
tapioca_disqus/resource_mapping/__init__.py
tapioca_disqus/resource_mapping/applications.py
tapioca_disqus/resource_mapping/blacklists.py
tapioca_disqus/resource_mapping/category.py
tapioca_disqus/resource_mapping/exports.py
tapioca_disqus/resource_mapping/forums.py
tapioca_disqus/resource_mapping/imports.py
tapioca_disqus/resource_mapping/posts.py
tapioca_disqus/resource_mapping/threads.py
tapioca_disqus/resource_mapping/topics.py
tapioca_disqus/resource_mapping/trends.py
tapioca_disqus/resource_mapping/users.py
tapioca_disqus/resource_mapping/whitelists.py
tapioca_disqus/resource_mapping/__pycache__/__init__.cpython-34.pyc
tapioca_disqus/resource_mapping/__pycache__/applications.cpython-34.pyc
tapioca_disqus/resource_mapping/__pycache__/blacklists.cpython-34.pyc
tapioca_disqus/resource_mapping/__pycache__/category.cpython-34.pyc
tapioca_disqus/resource_mapping/__pycache__/exports.cpython-34.pyc
tapioca_disqus/resource_mapping/__pycache__/forums.cpython-34.pyc
tapioca_disqus/resource_mapping/__pycache__/imports.cpython-34.pyc
tapioca_disqus/resource_mapping/__pycache__/posts.cpython-34.pyc
tapioca_disqus/resource_mapping/__pycache__/threads.cpython-34.pyc
tapioca_disqus/resource_mapping/__pycache__/topics.cpython-34.pyc
tapioca_disqus/resource_mapping/__pycache__/trends.cpython-34.pyc
tapioca_disqus/resource_mapping/__pycache__/users.cpython-34.pyc
tapioca_disqus/resource_mapping/__pycache__/whitelists.cpython-34.pyc