Metadata-Version: 1.1
Name: tapioca-disqus
Version: 0.1.1
Summary: Disqus API wrapper using tapioca
Home-page: https://github.com/marctc/tapioca-disqus
Author: Marc Tudurí
Author-email: marctc@gmail.com
License: MIT
Keywords: disqus python tapioca wrapper
Platform: UNKNOWN
Classifier: Development Status :: 5 - Production/Stable
Classifier: Intended Audience :: Developers
Classifier: License :: OSI Approved :: MIT License
Classifier: Natural Language :: English
Classifier: Programming Language :: Python :: 2
Classifier: Programming Language :: Python :: 2.7
Classifier: Programming Language :: Python :: 3
Classifier: Programming Language :: Python :: 3.1
Classifier: Programming Language :: Python :: 3.2
Classifier: Programming Language :: Python :: 3.3
Classifier: Programming Language :: Python :: 3.4
